Metadata-Version: 2.1
Name: custom-bgr
Version: 1.0
Summary: Customized background removal app
Home-page: https://github.com/Rishabh20539011/Custom_BGR_APP
Author: Rishabh Dwivedi
Author-email: dwivedi.rishabh95@gmail.com
Keywords: unet background removal,pretrained background removal,background removal,remove background,deep learning app,machine learning app
Classifier: Development Status :: 5 - Production/Stable
Classifier: Environment :: Web Environment
Classifier: Intended Audience :: Developers
Classifier: Natural Language :: English
Classifier: Operating System :: OS Independent
Classifier: Programming Language :: Python :: 3.10
Classifier: Topic :: Scientific/Engineering :: Artificial Intelligence
Requires-Python: >=3.10.4
Requires-Dist: absl-py ==1.4.0
Requires-Dist: aiohttp ==3.8.4
Requires-Dist: aiosignal ==1.3.1
Requires-Dist: albumentations ==1.3.0
Requires-Dist: argon2-cffi ==21.3.0
Requires-Dist: argon2-cffi-bindings ==21.2.0
Requires-Dist: async-timeout ==4.0.2
Requires-Dist: attrs ==22.2.0
Requires-Dist: backcall ==0.2.0
Requires-Dist: beautifulsoup4 ==4.11.1
Requires-Dist: bleach ==5.0.1
Requires-Dist: cachetools ==5.3.0
Requires-Dist: cffi ==1.15.1
Requires-Dist: charset-normalizer ==3.1.0
Requires-Dist: comm ==0.1.1
Requires-Dist: decorator ==5.1.1
Requires-Dist: defusedxml ==0.7.1
Requires-Dist: efficientnet-pytorch ==0.7.1
Requires-Dist: filelock ==3.11.0
Requires-Dist: frozenlist ==1.3.3
Requires-Dist: fsspec ==2023.4.0
Requires-Dist: future ==0.18.3
Requires-Dist: google-auth ==2.17.3
Requires-Dist: google-auth-oauthlib ==1.0.0
Requires-Dist: grpcio ==1.53.0
Requires-Dist: huggingface-hub ==0.13.4
Requires-Dist: idna ==3.4
Requires-Dist: imageio ==2.27.0
Requires-Dist: imagezmq ==1.1.1
Requires-Dist: importlib-metadata ==6.3.0
Requires-Dist: imutils ==0.5.4
Requires-Dist: install ==1.3.5
Requires-Dist: ipython-genutils ==0.2.0
Requires-Dist: ipywidgets ==8.0.2
Requires-Dist: Jinja2 ==3.1.2
Requires-Dist: joblib ==1.2.0
Requires-Dist: jupyter ==1.0.0
Requires-Dist: jupyter-console ==6.4.4
Requires-Dist: jupyterlab-pygments ==0.2.2
Requires-Dist: jupyterlab-widgets ==3.0.3
Requires-Dist: lazy-loader ==0.2
Requires-Dist: Markdown ==3.4.3
Requires-Dist: MarkupSafe ==2.1.1
Requires-Dist: matplotlib-inline ==0.1.6
Requires-Dist: mistune ==2.0.4
Requires-Dist: multidict ==6.0.4
Requires-Dist: munch ==2.5.0
Requires-Dist: networkx ==3.1
Requires-Dist: numpy ==1.24.2
Requires-Dist: oauthlib ==3.2.2
Requires-Dist: opencv-python ==4.7.0.72
Requires-Dist: opencv-python-headless ==4.7.0.72
Requires-Dist: packaging ==21.3
Requires-Dist: pandas ==2.0.0
Requires-Dist: pandocfilters ==1.5.0
Requires-Dist: parso ==0.8.3
Requires-Dist: pickleshare ==0.7.5
Requires-Dist: Pillow ==9.5.0
Requires-Dist: platformdirs ==2.5.4
Requires-Dist: pretrainedmodels ==0.7.4
Requires-Dist: protobuf ==4.22.3
Requires-Dist: ptyprocess ==0.7.0
Requires-Dist: pure-eval ==0.2.2
Requires-Dist: pyasn1 ==0.4.8
Requires-Dist: pyasn1-modules ==0.2.8
Requires-Dist: pycparser ==2.21
Requires-Dist: pyDeprecate ==0.3.1
Requires-Dist: Pygments ==2.13.0
Requires-Dist: pyparsing ==3.0.9
Requires-Dist: python-dateutil ==2.8.2
Requires-Dist: python-dotenv ==0.21.0
Requires-Dist: pytorch-lightning ==1.5.4
Requires-Dist: pytz ==2023.3
Requires-Dist: PyWavelets ==1.4.1
Requires-Dist: PyYAML ==6.0
Requires-Dist: pyzmq ==24.0.1
Requires-Dist: qtconsole ==5.4.0
Requires-Dist: QtPy ==2.3.0
Requires-Dist: qudida ==0.0.4
Requires-Dist: requests ==2.28.2
Requires-Dist: requests-oauthlib ==1.3.1
Requires-Dist: rsa ==4.9
Requires-Dist: scikit-image ==0.20.0
Requires-Dist: scikit-learn ==1.2.2
Requires-Dist: scipy ==1.9.1
Requires-Dist: segmentation-models-pytorch ==0.3.2
Requires-Dist: Send2Trash ==1.8.0
Requires-Dist: six ==1.16.0
Requires-Dist: sniffio ==1.3.0
Requires-Dist: soupsieve ==2.3.2.post1
Requires-Dist: tensorboard ==2.12.1
Requires-Dist: tensorboard-data-server ==0.7.0
Requires-Dist: tensorboard-plugin-wit ==1.8.1
Requires-Dist: threadpoolctl ==3.1.0
Requires-Dist: tifffile ==2023.4.12
Requires-Dist: timm ==0.6.12
Requires-Dist: torch ==2.0.1
Requires-Dist: torchaudio ==2.0.2
Requires-Dist: torchmetrics ==1.2.0
Requires-Dist: torchvision ==0.15.2
Requires-Dist: tornado ==6.2
Requires-Dist: tqdm ==4.65.0
Requires-Dist: typing-extensions ==4.5.0
Requires-Dist: tzdata ==2023.3
Requires-Dist: urllib3 ==1.26.15
Requires-Dist: wcwidth ==0.2.5
Requires-Dist: webencodings ==0.5.1
Requires-Dist: Werkzeug ==2.2.3
Requires-Dist: widgetsnbextension ==4.0.3
Requires-Dist: yarl ==1.8.2
Requires-Dist: zipp ==3.15.0
Requires-Dist: fastapi
Requires-Dist: uvicorn
